MANIFEST.in
README.txt
setup.py
docs/HISTORY.txt
src/zeam/__init__.py
src/zeam.form.rdb.egg-info/PKG-INFO
src/zeam.form.rdb.egg-info/SOURCES.txt
src/zeam.form.rdb.egg-info/dependency_links.txt
src/zeam.form.rdb.egg-info/entry_points.txt
src/zeam.form.rdb.egg-info/namespace_packages.txt
src/zeam.form.rdb.egg-info/not-zip-safe
src/zeam.form.rdb.egg-info/requires.txt
src/zeam.form.rdb.egg-info/top_level.txt
src/zeam/form/__init__.py
src/zeam/form/rdb/__init__.py
src/zeam/form/rdb/configure.zcml
src/zeam/form/rdb/factories.py
src/zeam/form/rdb/fields.py
src/zeam/form/rdb/ftesting.zcml
src/zeam/form/rdb/source.py
src/zeam/form/rdb/testing.py
src/zeam/form/rdb/tests/__init__.py
src/zeam/form/rdb/tests/columns.txt
src/zeam/form/rdb/tests/tables.txt
src/zeam/form/rdb/tests/test_doctest.py