Metadata-Version: 1.0
Name: zeam.form.rdb
Version: 1.0
Summary: Extra SQLAlchemy support for zeam.form
Home-page: http://pypi.python.org/pypi/zeam.form.rdb
Author: Sylvain Viollon
Author-email: thefunny@gmail.com
License: BSD
Keywords: zeam form rdb
Platform: UNKNOWN
Classifier: Programming Language :: Python
Classifier: Topic :: Software Development :: Libraries :: Python Modules
